{"info":{"file":"lib/adapter.js","fileShort":"lib/adapter.js","fileSafe":"lib_adapter_js","link":"files/lib_adapter_js/index.html"},"complexity":{"aggregate":{"line":1,"complexity":{"sloc":{"physical":259,"logical":161},"cyclomatic":28,"halstead":{"operators":{"distinct":18,"total":423,"identifiers":["__stripped__"]},"operands":{"distinct":107,"total":499,"identifiers":["__stripped__"]},"length":922,"vocabulary":125,"difficulty":41.97196261682243,"volume":6422.453110458445,"effort":269562.9618604568,"bugs":2.140817703486148,"time":14975.720103358712},"params":34}},"functions":[{"name":"Adapter","line":9,"complexity":{"sloc":{"physical":94,"logical":6},"cyclomatic":1,"halstead":{"operators":{"distinct":8,"total":20,"identifiers":["__stripped__"]},"operands":{"distinct":16,"total":26,"identifiers":["__stripped__"]},"length":46,"vocabulary":24,"difficulty":6.5,"volume":210.90827503317323,"effort":1370.9037877156259,"bugs":0.07030275834439108,"time":76.161321539757},"params":2}},{"name":"Backbone.sync","line":14,"complexity":{"sloc":{"physical":85,"logical":27},"cyclomatic":7,"halstead":{"operators":{"distinct":10,"total":79,"identifiers":["__stripped__"]},"operands":{"distinct":32,"total":83,"identifiers":["__stripped__"]},"length":162,"vocabulary":42,"difficulty":12.96875,"volume":873.5554224901592,"effort":11328.921885419253,"bugs":0.2911851408300531,"time":629.3845491899585},"params":3}},{"name":"<anonymous>","line":36,"complexity":{"sloc":{"physical":3,"logical":1},"cyclomatic":1,"halstead":{"operators":{"distinct":2,"total":2,"identifiers":["__stripped__"]},"operands":{"distinct":3,"total":4,"identifiers":["__stripped__"]},"length":6,"vocabulary":5,"difficulty":1.3333333333333333,"volume":13.931568569324174,"effort":18.575424759098897,"bugs":0.004643856189774725,"time":1.0319680421721609},"params":1}},{"name":"<anonymous>","line":33,"complexity":{"sloc":{"physical":3,"logical":1},"cyclomatic":1,"halstead":{"operators":{"distinct":2,"total":2,"identifiers":["__stripped__"]},"operands":{"distinct":2,"total":2,"identifiers":["__stripped__"]},"length":4,"vocabulary":4,"difficulty":1,"volume":8,"effort":8,"bugs":0.0026666666666666666,"time":0.4444444444444444},"params":0}},{"name":"<anonymous>","line":24,"complexity":{"sloc":{"physical":9,"logical":6},"cyclomatic":3,"halstead":{"operators":{"distinct":7,"total":20,"identifiers":["__stripped__"]},"operands":{"distinct":8,"total":22,"identifiers":["__stripped__"]},"length":42,"vocabulary":15,"difficulty":9.625,"volume":164.0894050155578,"effort":1579.3605232747436,"bugs":0.05469646833851926,"time":87.7422512930413},"params":1}},{"name":"<anonymous>","line":54,"complexity":{"sloc":{"physical":11,"logical":6},"cyclomatic":2,"halstead":{"operators":{"distinct":4,"total":10,"identifiers":["__stripped__"]},"operands":{"distinct":10,"total":13,"identifiers":["__stripped__"]},"length":23,"vocabulary":14,"difficulty":2.6,"volume":87.56916320732489,"effort":227.67982433904473,"bugs":0.029189721069108297,"time":12.648879129946929},"params":1}},{"name":"<anonymous>","line":70,"complexity":{"sloc":{"physical":9,"logical":5},"cyclomatic":2,"halstead":{"operators":{"distinct":4,"total":8,"identifiers":["__stripped__"]},"operands":{"distinct":6,"total":9,"identifiers":["__stripped__"]},"length":17,"vocabulary":10,"difficulty":3,"volume":56.472777613085164,"effort":169.4183328392555,"bugs":0.01882425920436172,"time":9.412129602180862},"params":1}},{"name":"<anonymous>","line":85,"complexity":{"sloc":{"physical":9,"logical":5},"cyclomatic":2,"halstead":{"operators":{"distinct":4,"total":8,"identifiers":["__stripped__"]},"operands":{"distinct":6,"total":9,"identifiers":["__stripped__"]},"length":17,"vocabulary":10,"difficulty":3,"volume":56.472777613085164,"effort":169.4183328392555,"bugs":0.01882425920436172,"time":9.412129602180862},"params":1}},{"name":"Adapter.CollectionOverwrite","line":104,"complexity":{"sloc":{"physical":63,"logical":2},"cyclomatic":1,"halstead":{"operators":{"distinct":3,"total":6,"identifiers":["__stripped__"]},"operands":{"distinct":4,"total":8,"identifiers":["__stripped__"]},"length":14,"vocabulary":7,"difficulty":3,"volume":39.302968908806456,"effort":117.90890672641936,"bugs":0.01310098963626882,"time":6.550494818134409},"params":1}},{"name":"Collection.extend","line":107,"complexity":{"sloc":{"physical":59,"logical":8},"cyclomatic":2,"halstead":{"operators":{"distinct":7,"total":29,"identifiers":["__stripped__"]},"operands":{"distinct":18,"total":33,"identifiers":["__stripped__"]},"length":62,"vocabulary":25,"difficulty":6.416666666666666,"volume":287.9190837660329,"effort":1847.480787498711,"bugs":0.09597302792201096,"time":102.63782152770617},"params":1}},{"name":"<anonymous>.nuke","line":116,"complexity":{"sloc":{"physical":23,"logical":3},"cyclomatic":1,"halstead":{"operators":{"distinct":6,"total":17,"identifiers":["__stripped__"]},"operands":{"distinct":11,"total":17,"identifiers":["__stripped__"]},"length":34,"vocabulary":17,"difficulty":4.636363636363637,"volume":138.97373660251156,"effort":644.3327787934628,"bugs":0.04632457886750385,"time":35.79626548852571},"params":1}},{"name":"<anonymous>","line":134,"complexity":{"sloc":{"physical":4,"logical":2},"cyclomatic":1,"halstead":{"operators":{"distinct":2,"total":3,"identifiers":["__stripped__"]},"operands":{"distinct":5,"total":7,"identifiers":["__stripped__"]},"length":10,"vocabulary":7,"difficulty":1.4,"volume":28.07354922057604,"effort":39.302968908806456,"bugs":0.009357849740192013,"time":2.1834982727114696},"params":1}},{"name":"<anonymous>","line":124,"complexity":{"sloc":{"physical":10,"logical":4},"cyclomatic":2,"halstead":{"operators":{"distinct":5,"total":7,"identifiers":["__stripped__"]},"operands":{"distinct":7,"total":9,"identifiers":["__stripped__"]},"length":16,"vocabulary":12,"difficulty":3.2142857142857144,"volume":57.359400011538504,"effort":184.36950003708805,"bugs":0.01911980000384617,"time":10.242750002060447},"params":1}},{"name":"<anonymous>","line":130,"complexity":{"sloc":{"physical":3,"logical":1},"cyclomatic":1,"halstead":{"operators":{"distinct":1,"total":1,"identifiers":["__stripped__"]},"operands":{"distinct":2,"total":3,"identifiers":["__stripped__"]},"length":4,"vocabulary":3,"difficulty":0.75,"volume":6.339850002884625,"effort":4.754887502163469,"bugs":0.002113283334294875,"time":0.2641604167868594},"params":1}},{"name":"<anonymous>","line":121,"complexity":{"sloc":{"physical":3,"logical":3},"cyclomatic":1,"halstead":{"operators":{"distinct":4,"total":5,"identifiers":["__stripped__"]},"operands":{"distinct":6,"total":8,"identifiers":["__stripped__"]},"length":13,"vocabulary":10,"difficulty":2.6666666666666665,"volume":43.18506523353572,"effort":115.16017395609524,"bugs":0.014395021744511906,"time":6.397787442005291},"params":1}},{"name":"<anonymous>.fetchFilter","line":140,"complexity":{"sloc":{"physical":18,"logical":5},"cyclomatic":2,"halstead":{"operators":{"distinct":10,"total":13,"identifiers":["__stripped__"]},"operands":{"distinct":8,"total":13,"identifiers":["__stripped__"]},"length":26,"vocabulary":18,"difficulty":8.125,"volume":108.41805003750011,"effort":880.8966565546884,"bugs":0.036139350012500036,"time":48.938703141927135},"params":1}},{"name":"<anonymous>","line":143,"complexity":{"sloc":{"physical":11,"logical":3},"cyclomatic":1,"halstead":{"operators":{"distinct":6,"total":6,"identifiers":["__stripped__"]},"operands":{"distinct":7,"total":8,"identifiers":["__stripped__"]},"length":14,"vocabulary":13,"difficulty":3.4285714285714284,"volume":51.80615605397529,"effort":177.62110647077242,"bugs":0.01726871868465843,"time":9.867839248376246},"params":1}},{"name":"<anonymous>","line":146,"complexity":{"sloc":{"physical":5,"logical":2},"cyclomatic":2,"halstead":{"operators":{"distinct":7,"total":8,"identifiers":["__stripped__"]},"operands":{"distinct":7,"total":11,"identifiers":["__stripped__"]},"length":19,"vocabulary":14,"difficulty":5.5,"volume":72.33974351909447,"effort":397.8685893550196,"bugs":0.024113247839698156,"time":22.10381051972331},"params":2}},{"name":"<anonymous>.fetchOne","line":159,"complexity":{"sloc":{"physical":3,"logical":1},"cyclomatic":1,"halstead":{"operators":{"distinct":3,"total":4,"identifiers":["__stripped__"]},"operands":{"distinct":4,"total":5,"identifiers":["__stripped__"]},"length":9,"vocabulary":7,"difficulty":1.875,"volume":25.26619429851844,"effort":47.374114309722074,"bugs":0.008422064766172813,"time":2.6318952394290043},"params":1}},{"name":"Adapter.ModelOverwrite","line":168,"complexity":{"sloc":{"physical":90,"logical":4},"cyclomatic":1,"halstead":{"operators":{"distinct":3,"total":12,"identifiers":["__stripped__"]},"operands":{"distinct":6,"total":14,"identifiers":["__stripped__"]},"length":26,"vocabulary":9,"difficulty":3.5,"volume":82.41805003750012,"effort":288.4631751312504,"bugs":0.027472683345833374,"time":16.025731951736134},"params":1}},{"name":"Model.extend","line":171,"complexity":{"sloc":{"physical":15,"logical":8},"cyclomatic":2,"halstead":{"operators":{"distinct":6,"total":24,"identifiers":["__stripped__"]},"operands":{"distinct":15,"total":30,"identifiers":["__stripped__"]},"length":54,"vocabulary":21,"difficulty":6,"volume":237.1851408300531,"effort":1423.1108449803185,"bugs":0.0790617136100177,"time":79.06171361001769},"params":1}},{"name":"Model.find","line":187,"complexity":{"sloc":{"physical":48,"logical":6},"cyclomatic":1,"halstead":{"operators":{"distinct":7,"total":24,"identifiers":["__stripped__"]},"operands":{"distinct":17,"total":25,"identifiers":["__stripped__"]},"length":49,"vocabulary":24,"difficulty":5.147058823529412,"volume":224.66316253533668,"effort":1156.3545130495272,"bugs":0.07488772084511222,"time":64.2419173916404},"params":2}},{"name":"<anonymous>","line":229,"complexity":{"sloc":{"physical":3,"logical":1},"cyclomatic":1,"halstead":{"operators":{"distinct":2,"total":2,"identifiers":["__stripped__"]},"operands":{"distinct":3,"total":4,"identifiers":["__stripped__"]},"length":6,"vocabulary":5,"difficulty":1.3333333333333333,"volume":13.931568569324174,"effort":18.575424759098897,"bugs":0.004643856189774725,"time":1.0319680421721609},"params":1}},{"name":"<anonymous>","line":216,"complexity":{"sloc":{"physical":13,"logical":16},"cyclomatic":6,"halstead":{"operators":{"distinct":11,"total":29,"identifiers":["__stripped__"]},"operands":{"distinct":14,"total":34,"identifiers":["__stripped__"]},"length":63,"vocabulary":25,"difficulty":13.357142857142856,"volume":292.5629399558076,"effort":3907.80498369543,"bugs":0.09752097998526921,"time":217.10027687196833},"params":0}},{"name":"<anonymous>","line":195,"complexity":{"sloc":{"physical":21,"logical":9},"cyclomatic":3,"halstead":{"operators":{"distinct":7,"total":20,"identifiers":["__stripped__"]},"operands":{"distinct":13,"total":25,"identifiers":["__stripped__"]},"length":45,"vocabulary":20,"difficulty":6.730769230769231,"volume":194.4867642699313,"effort":1309.0455287399222,"bugs":0.06482892142331044,"time":72.72475159666234},"params":1}},{"name":"<anonymous>","line":202,"complexity":{"sloc":{"physical":5,"logical":2},"cyclomatic":2,"halstead":{"operators":{"distinct":7,"total":10,"identifiers":["__stripped__"]},"operands":{"distinct":7,"total":13,"identifiers":["__stripped__"]},"length":23,"vocabulary":14,"difficulty":6.5,"volume":87.56916320732489,"effort":569.1995608476118,"bugs":0.029189721069108297,"time":31.62219782486732},"params":2}},{"name":"Model.get","line":236,"complexity":{"sloc":{"physical":21,"logical":4},"cyclomatic":1,"halstead":{"operators":{"distinct":6,"total":12,"identifiers":["__stripped__"]},"operands":{"distinct":11,"total":14,"identifiers":["__stripped__"]},"length":26,"vocabulary":17,"difficulty":3.8181818181818183,"volume":106.27403387250884,"effort":405.77358387685194,"bugs":0.03542467795750295,"time":22.54297688204733},"params":2}},{"name":"<anonymous>","line":240,"complexity":{"sloc":{"physical":14,"logical":10},"cyclomatic":4,"halstead":{"operators":{"distinct":7,"total":15,"identifiers":["__stripped__"]},"operands":{"distinct":10,"total":23,"identifiers":["__stripped__"]},"length":38,"vocabulary":17,"difficulty":8.049999999999999,"volume":155.3235879675129,"effort":1250.3548831384787,"bugs":0.0517745293225043,"time":69.46416017435993},"params":2}}],"maintainability":70.01475426303097,"params":1.2142857142857142,"module":"lib/adapter.js"},"jshint":{"messages":[]}}